Workbook
Name _xlchart.1: Planilha1!$B$37:$B$43
Name aporte: Planilha1!$D$18
Name _xlchart.4: Planilha1!$D$36
Name _xlchart.3: Planilha1!$C$37:$C$43
Name patrimonio: Planilha1!$D$21
Name _xlchart.0: Planilha1!$B$36
Name rendimento_carteira: Planilha1!$D$14
Name _xlchart.5: Planilha1!$D$37:$D$43
Name taxa_mensal: Planilha1!$D$20
Name qtd_ano: Planilha1!$D$19
Name _xlchart.2: Planilha1!$C$36

Sheet Planilha1
B12: CONFIGURAÇÕES
B13: Salário | D13: 2000
B14: Rendimento Carteira | D14: 0.006
B15: Sugestão de Investimento (30%) | D15: =D13*30% -> 600
B17: INVESTIMENTO MENSAL
B18: Quanto investir por mês ? | D18: 98
B19: Por Quantos Anos ? | D19: 5
B20: Taxa de Rendimento mensal ? | D20: 0.01079
B21: Patrimônio acumulado ? | D21: =FV(taxa_mensal,qtd_ano*12,aporte*-1) -> 8210.1376
B22: Dividendos Mensais ? | D22: =patrimonio*rendimento_carteira -> 49.260825
B24: Cenários | D24: Dividendo
A25: 2 | B25: Quanto em 2 Anos ? | C25: =FV($D$20,$A25*12,$D$18*-1) -> 2668.3075 | D25: =C25*$D$20 -> 28.791038
A26: 5 | B26: Quanto em 5 Anos ? | C26: =FV($D$20,$A26*12,$D$18*-1) -> 8210.1376 | D26: =C26*$D$20 -> 88.587384
A27: 10 | B27: Quanto em 10 Anos ? | C27: =FV($D$20,$A27*12,$D$18*-1) -> 23841.853 | D27: =C27*$D$20 -> 257.25359
A28: 20 | B28: Quanto em 20 Anos ? | C28: =FV($D$20,$A28*12,$D$18*-1) -> 110269.44 | D28: =C28*$D$20 -> 1189.8073
A29: 30 | B29: Quanto em 30 Anos ? | C29: =FV($D$20,$A29*12,$D$18*-1) -> 423572.63 | D29: =C29*$D$20 -> 4570.3486
B33: PERFIL | C33: Moderado
B34: VALOR A SER INVESTIDO POR MÊS | C34: =aporte -> 98
B36: TIPO DE FII | C36: Percentual Sugerido | D36: Valores
B37: PAPEL | C37: =VLOOKUP($C$33&"-"&$B37,Planilha2!$A:$D,4,FALSE) -> 0.32 | D37: =C37*$C$34 -> 31.36
B38: TIJOLO | C38: =VLOOKUP($C$33&"-"&$B38,Planilha2!$A:$D,4,FALSE) -> 0.35 | D38: =C38*$C$34 -> 34.3
B39: HÍBRIDOS | C39: =VLOOKUP($C$33&"-"&$B39,Planilha2!$A:$D,4,FALSE) -> 0.08 | D39: =C39*$C$34 -> 7.84
B40: FOFs | C40: =VLOOKUP($C$33&"-"&$B40,Planilha2!$A:$D,4,FALSE) -> 0.05 | D40: =C40*$C$34 -> 4.9
B41: DESENVOLVIMENTO | C41: =VLOOKUP($C$33&"-"&$B41,Planilha2!$A:$D,4,FALSE) -> 0.1 | D41: =C41*$C$34 -> 9.8
B42: HOTELARIAS | C42: =VLOOKUP($C$33&"-"&$B42,Planilha2!$A:$D,4,FALSE) -> 0.1 | D42: =C42*$C$34 -> 9.8
D43: =SUM(D37:D42) -> 98

Sheet Planilha2
A2: CHAVE | B2: PERFIL | C2: TIPO DE FII | D2: %
A3: =B3&"-"&C3 -> Conservador-PAPEL | B3: Conservador | C3: PAPEL | D3: 0.3 | H3: %
A4: =B4&"-"&C4 -> Conservador-TIJOLO | B4: Conservador | C4: TIJOLO | D4: 0.5 | G4: Moderado-PAPEL | H4: =VLOOKUP(G4,$A:$D,4,FALSE) -> 0.32
A5: =B5&"-"&C5 -> Conservador-HÍBRIDOS | B5: Conservador | C5: HÍBRIDOS | D5: 0.1
A6: =B6&"-"&C6 -> Conservador-FOFs | B6: Conservador | C6: FOFs | D6: 0.1
A7: =B7&"-"&C7 -> Conservador-DESENVOLVIMENTO | B7: Conservador | C7: DESENVOLVIMENTO | D7: 0
A8: =B8&"-"&C8 -> Conservador-HOTELARIAS | B8: Conservador | C8: HOTELARIAS | D8: 0
A9: =B9&"-"&C9 -> Moderado-PAPEL | B9: Moderado | C9: PAPEL | D9: 0.32
A10: =B10&"-"&C10 -> Moderado-TIJOLO | B10: Moderado | C10: TIJOLO | D10: 0.35
A11: =B11&"-"&C11 -> Moderado-HÍBRIDOS | B11: Moderado | C11: HÍBRIDOS | D11: 0.08
A12: =B12&"-"&C12 -> Moderado-FOFs | B12: Moderado | C12: FOFs | D12: 0.05
A13: =B13&"-"&C13 -> Moderado-DESENVOLVIMENTO | B13: Moderado | C13: DESENVOLVIMENTO | D13: 0.1
A14: =B14&"-"&C14 -> Moderado-HOTELARIAS | B14: Moderado | C14: HOTELARIAS | D14: 0.1
A15: =B15&"-"&C15 -> Agressivo-PAPEL | B15: Agressivo | C15: PAPEL | D15: 0.5
A16: =B16&"-"&C16 -> Agressivo-TIJOLO | B16: Agressivo | C16: TIJOLO | D16: 0.1
... A20: =B20&"-"&C20 -> Agressivo-HOTELARIAS | B20: Agressivo | C20: HOTELARIAS | D20: 0.1
